{
  "name": "SynthWave 84",
  "type": "dark",
  "semanticHighlighting": true,
  "semanticTokenColors": {
    "enumMember": {
      "foreground": "#56b6c2"
    },
    "variable.constant": {
      "foreground": "#d19a66"
    },
    "variable.defaultLibrary": {
      "foreground": "#e5c07b"
    },
    "variable:dart": {
      "foreground": "#d19a66"
    },
    "property:dart": {
      "foreground": "#d19a66"
    },
    "annotation:dart": {
      "foreground": "#d19a66"
    },
    "parameter.label:dart": {
      "foreground": "#abb2bf"
    },
    "macro": {
      "foreground": "#d19a66"
    },
    "tomlArrayKey": {
      "foreground": "#e5c07b"
    },
    "memberOperatorOverload": {
      "foreground": "#c678dd"
    }
  },
  "tokenColors": [
    {
      "name": "Comment",
      "scope": [
        "comment", 
        "string.quoted.docstring.multi.python", 
        "string.quoted.docstring.multi.python punctuation.definition.string.begin.python",
        "string.quoted.docstring.multi.python punctuation.definition.string.end.python"
      ],
      "settings": {
        "foreground": "#7a7a7a",
        "fontStyle": "italic"
      }
    },
    {
      "name": "String",
      "scope": [
        "string.quoted",
        "string.template",
        "punctuation.definition.string"
      ],
      "settings": {
        "foreground": "#98c379"
      }
    },
    {
      "name": "Punctuation within templates",
      "scope": "string.template meta.embedded.line",
      "settings": {
        "foreground": "#b6b1b1"
      }
    },
    {
      "name": "Variable",
      "scope": ["variable", "entity.name.variable"],
      "settings": {
        "foreground": "#ff7edb"
      }
    },
    {
      "name": "Language variable",
      "scope": "variable.language",
      "settings": {
        "foreground": "#fe4450",
        "fontStyle": "bold"
      }
    },
    {
      "name": "Parameter",
      "scope": "variable.parameter",
      "settings": {
        "fontStyle": "italic"
      }
    },
    {
      "name": "Storage (declaration or modifier keyword)",
      "scope": ["storage.type", "storage.modifier"],
      "settings": {
        "foreground": "#fede5d"
      }
    },
    {
      "name": "Constants",
      "scope": "constant",
      "settings": {
        "foreground": "#f97e72"
      }
    },
    {
      "name": "Regex",
      "scope": "string.regexp",
      "settings": {
        "foreground": "#f97e72"
      }
    },
    {
      "name": "Number",
      "scope": "constant.numeric",
      "settings": {
        "foreground": "#f97e72"
      }
    },
    {
      "name": "Language constant (boolean, null)",
      "scope": "constant.language",
      "settings": {
        "foreground": "#f97e72"
      }
    },
    {
      "name": "Character escape",
      "scope": "constant.character.escape",
      "settings": {
        "foreground": "#36f9f6"
      }
    },
    {
      "name": "Entity",
      "scope": "entity.name",
      "settings": {
        "foreground": "#fe4450"
      }
    },
    {
      "name": "HTML or XML tag",
      "scope": "entity.name.tag",
      "settings": {
        "foreground": "#72f1b8"
      }
    },
    {
      "name": "HTML or XML tag brackets",
      "scope": ["punctuation.definition.tag"],
      "settings": {
        "foreground": "#36f9f6"
      }
    },
    {
      "name": "Tag attribute",
      "scope": "entity.other.attribute-name",
      "settings": {
        "foreground": "#fede5d"
      }
    },
    {
      "name": "Tag attribute HTML",
      "scope": "entity.other.attribute-name.html",
      "settings": {
        "foreground": "#fede5d",
        "fontStyle": "italic"
      }
    },
    {
      "name": "Class",
      "scope": ["entity.name.type", "meta.attribute.class.html"],
      "settings": {
        "foreground": "#fe4450"
      }
    },
    {
      "name": "Inherited class",
      "scope": "entity.other.inherited-class",
      "settings": {
        "foreground": "#D50"
      }
    },
    {
      "name": "Function",
      "scope": ["entity.name.function", "variable.function"],
      "settings": {
        "foreground": "#36f9f6"
      }
    },
    {
      "name": "JS Export",
      "scope": ["keyword.control.export.js", "keyword.control.import.js"],
      "settings": {
        "foreground": "#72f1b8"
      }
    },
    {
      "name": "JS Numerics",
      "scope": ["constant.numeric.decimal.js"],
      "settings": {
        "foreground": "#f97e72"
      }
    },
    {
      "name": "Keyword",
      "scope": "keyword",
      "settings": {
        "foreground": "#fede5d"
      }
    },
    {
      "name": "Control keyword",
      "scope": "keyword.control",
      "settings": {
        "foreground": "#3364eb"
      }
    },
    {
      "name": "Operator",
      "scope": "keyword.operator",
      "settings": {
        "foreground": "#ffffff"
      }
    },
    {
      "name": "Special operator",
      "scope": [
        "keyword.operator.new",
        "keyword.operator.expression",
        "keyword.operator.logical"
      ],
      "settings": {
        "foreground": "#fede5d"
      }
    },
    {
      "name": "Unit",
      "scope": "keyword.other.unit",
      "settings": {
        "foreground": "#f97e72"
      }
    },
    {
      "name": "Support",
      "scope": "support",
      "settings": {
        "foreground": "#fe4450"
      }
    },
    {
      "name": "Support function",
      "scope": "support.function",
      "settings": {
        "foreground": "#36f9f6"
      }
    },
    {
      "name": "Support variable",
      "scope": "support.variable",
      "settings": {
        "foreground": "#ff7edb"
      }
    },
    {
      "name": "Object literal key / property",
      "scope": ["meta.object-literal.key", "support.type.property-name"],
      "settings": {
        "foreground": "#ff7edb"
      }
    },
    {
      "name": "Key-value separator",
      "scope": "punctuation.separator.key-value",
      "settings": {
        "foreground": "#b6b1b1"
      }
    },
    {
      "name": "Embedded punctuation",
      "scope": "punctuation.section.embedded",
      "settings": {
        "foreground": "#fe785d"
      }
    },
    {
      "name": "Template expression",
      "scope": [
        "punctuation.definition.template-expression.begin",
        "punctuation.definition.template-expression.end"
      ],
      "settings": {
        "foreground": "#72f1b8"
      }
    },
    {
      "name": "CSS property",
      "scope": [
        "support.type.property-name.css"
      ],
      "settings": {
        "foreground": "#b5b5b5"
      }
    },
    {
      "name": "Json key",
      "scope": [
        "support.type.property-name.json"
      ],
      "settings": {
        "foreground": "#e06c75"
      }
    },
    {
      "name": "JS Switch control",
      "scope": "switch-block.expr.js",
      "settings": {
        "foreground": "#72f1b8"
      }
    },
    {
      "name": "JS object path",
      "scope": "variable.other.constant.property.js, variable.other.property.js",
      "settings": {
        "foreground": "#2ee2fa"
      },
    },
    {
      "name": "Color",
      "scope": "constant.other.color",
      "settings": {
        "foreground": "#f97e72"
      }
    },
    {
      "name": "Font names",
      "scope": "support.constant.font-name",
      "settings": {
        "foreground": "#f97e72"
      }
    },
    {
      "name": "CSS #id",
      "scope": "entity.other.attribute-name.id",
      "settings": {
        "foreground": "#36f9f6"
      }
    },
    {
      "name": "Pseudo CSS",
      "scope": [
        "entity.other.attribute-name.pseudo-element",
        "entity.other.attribute-name.pseudo-class"
      ],
      "settings": {
        "foreground": "#D50"
      }
    },
    {
      "name": "CSS support functions (rgb)",
      "scope": "support.function.misc.css",
      "settings": {
        "foreground": "#8daefa"
      }
    },
    {
      "name": "Markup heading",
      "scope": ["markup.heading", "entity.name.section"],
      "settings": {
        "foreground": "#ff7edb"
      }
    },
    {
      "name": "Markup text",
      "scope": ["text.html", "keyword.operator.assignment", ],
      "settings": {
        "foreground": "#ffffffee"
      }
    },
    {
      "name": "Markup quote",
      "scope": "markup.quote",
      "settings": {
        "foreground": "#b6b1b1cc",
        "fontStyle": "italic"
      }
    },
    {
      "name": "Markup list",
      "scope": "beginning.punctuation.definition.list",
      "settings": {
        "foreground": "#ff7edb"
      }
    },
    {
      "name": "Markup link",
      "scope": "markup.underline.link",
      "settings": {
        "foreground": "#D50"
      }
    },
    {
      "name": "Markup link description",
      "scope": "string.other.link.description",
      "settings": {
        "foreground": "#f97e72"
      }
    },
    {
      "name": "Python function call",
      "scope": "meta.function-call.generic.python",
      "settings": {
        "foreground": "#36f9f6"
      }
    },
    {
      "name": "Python variable params",
      "scope": "variable.parameter.function-call.python",
      "settings": {
        "foreground": "#72f1b8"
      }
    },
    {
      "name": "C# storage type",
      "scope": "storage.type.cs",
      "settings": {
        "foreground": "#fe4450"
      }
    },
    {
      "name": "C# local variable",
      "scope": "entity.name.variable.local.cs",
      "settings": {
        "foreground": "#ff7edb"
      }
    },
    {
      "name": "C# properties and fields",
      "scope": [
        "entity.name.variable.field.cs",
        "entity.name.variable.property.cs"
      ],
      "settings": {
        "foreground": "#ff7edb"
      }
    },
    {
      "name": "C placeholder",
      "scope": "constant.other.placeholder.c",
      "settings": {
        "foreground": "#72f1b8",
        "fontStyle": "italic"
      }
    },
    {
      "name": "C preprocessors",
      "scope": [
        "keyword.control.directive.include.c",
        "keyword.control.directive.define.c"
      ],
      "settings": {
        "foreground": "#72f1b8"
      }
    },
    {
      "name": "C storage modifier",
      "scope": "storage.modifier.c",
      "settings": {
        "foreground": "#fe4450"
      }
    },
    {
      "name": "C++ operators",
      "scope": "source.cpp keyword.operator",
      "settings": {
        "foreground": "#ffffff"
      }
    },
    {
      "name": "C++ placeholder",
      "scope": "constant.other.placeholder.cpp",
      "settings": {
        "foreground": "#72f1b8",
        "fontStyle": "italic"
      }
    },
    {
      "name": "C++ include",
      "scope": [
        "keyword.control.directive.include.cpp",
        "keyword.control.directive.define.cpp"
      ],
      "settings": {
        "foreground": "#233054"
      }
    },
    {
      "name": "C++ constant modifier",
      "scope": "storage.modifier.specifier.const.cpp",
      "settings": {
        "foreground": "#fe4450"
      }
    },
    {
      "name": "Elixir Classes",
      "scope": [
        "source.elixir support.type.elixir",
        "source.elixir meta.module.elixir entity.name.class.elixir"
      ],
      "settings": {
        "foreground": "#36f9f6"
      }
    },
    {
      "name": "Elixir Functions",
      "scope": "source.elixir entity.name.function",
      "settings": {
        "foreground": "#72f1b8"
      }
    },
    {
      "name": "Elixir Constants",
      "scope": [
        "source.elixir constant.other.symbol.elixir",
        "source.elixir constant.other.keywords.elixir"
      ],
      "settings": {
        "foreground": "#36f9f6"
      }
    },
    {
      "name": "Elixir String Punctuation",
      "scope": "source.elixir punctuation.definition.string",
      "settings": {
        "foreground": "#98c379"
      }
    },
    {
      "name": "Elixir",
      "scope": [
        "source.elixir variable.other.readwrite.module.elixir",
        "source.elixir variable.other.readwrite.module.elixir punctuation.definition.variable.elixir"
      ],
      "settings": {
        "foreground": "#72f1b8"
      }
    },
    {
      "name": "Elixir Binary Punctuation",
      "scope": "source.elixir .punctuation.binary.elixir",
      "settings": {
        "foreground": "#ff7edb",
        "fontStyle": "italic"
      }
    },
    {
      "name": "Clojure Globals",
      "scope": [
        "entity.global.clojure",
      ],
      "settings": {
        "foreground": "#36f9f6",
        "fontStyle": "bold"
      }
    },
    {
      "name": "Clojure Storage",
      "scope": [
        "storage.control.clojure"
      ],
      "settings": {
        "foreground": "#36f9f6",
        "fontStyle": "italic"
      }
    },
    {
      "name": "Clojure Metadata",
      "scope": [
        "meta.metadata.simple.clojure",
        "meta.metadata.map.clojure"
      ],
      "settings": {
        "foreground": "#fe4450",
        "fontStyle": "italic"
      }
    },
    {
      "name": "Clojure Macros, Quoted",
      "scope": [
        "meta.quoted-expression.clojure"
      ],
      "settings": {
        "fontStyle": "italic"
      }
    },
    {
      "name": "Clojure Symbols",
      "scope": [
        "meta.symbol.clojure"
      ],
      "settings": {
        "foreground": "#ff7edbff"
      }
    },
    {
      "name": "Go basic",
      "scope": "source.go",
      "settings": {
        "foreground": "#ff7edbff"
      }
    },
    {
      "name": "Go Function Calls",
      "scope": "source.go meta.function-call.go",
      "settings": {
        "foreground": "#36f9f6"
      }
    },
    {
      "name": "Go Keywords",
      "scope": [
        "source.go keyword.package.go",
        "source.go keyword.import.go",
        "source.go keyword.function.go",
        "source.go keyword.type.go",
        "source.go keyword.const.go",
        "source.go keyword.var.go",
        "source.go keyword.map.go",
        "source.go keyword.channel.go",
        "source.go keyword.control.go"
      ],
      "settings": {
        "foreground": "#fede5d",
      }
    },
    {
      "name": "Go interfaces",
      "scope": [
        "source.go storage.type",
        "source.go keyword.struct.go",
        "source.go keyword.interface.go",
      ],
      "settings": {
        "foreground": "#72f1b8",
      }
    },
    {
      "name": "Go Constants e.g. nil, string format (%s, %d, etc.)",
      "scope": [
        "source.go constant.language.go",
        "source.go constant.other.placeholder.go",
        "source.go variable"
      ],
      "settings": {
        "foreground": "#2EE2FA"
      }
    },
    {
      "name": "Markdown links and image paths",
      "scope": [
        "markup.underline.link.markdown",
        "markup.inline.raw.string.markdown"
      ],
      "settings": {
        "foreground": "#72f1b8",
        "fontStyle": "italic"
      }
    },
    {
      "name": "Markdown links and image paths",
      "scope": [
        "string.other.link.title.markdown"
      ],
      "settings": {
        "foreground": "#fede5d"
      }
    },
    {
      "name": "Markdown headings",
      "scope": [
        "markup.heading.markdown",
        "entity.name.section.markdown",
      ],
      "settings": {
        "foreground": "#ff7edb",
        "fontStyle": "bold"
      }
    },
    {
      "name": "Markdown italic",
      "scope": [
        "markup.italic.markdown",
      ],
      "settings": {
        "foreground": "#2EE2FA",
        "fontStyle": "italic"
      }
    },
    {
      "name": "Markdown bold",
      "scope": [
        "markup.bold.markdown",
      ],
      "settings": {
        "foreground": "#2EE2FA",
        "fontStyle": "bold"
      }
    },
    {
      "name": "Markdown quotes",
      "scope": [
        "punctuation.definition.quote.begin.markdown",
        "markup.quote.markdown",
      ],
      "settings": {
        "foreground": "#72f1b8",
      }
    },
    {
      "name": "Basic source colours",
      "scope": ["source.dart", "source.python", "source.scala"],
      "settings": {
        "foreground": "#ff7edbff"
      }
    },
    {
      "name": "Dart strings",
      "scope": [
        "string.interpolated.single.dart",
      ],
      "settings": {
        "foreground": "#f97e72",
      }
    },
    {
      "name": "Dart variable params",
      "scope": [
        "variable.parameter.dart",
      ],
      "settings": {
        "foreground": "#72f1b8",
      }
    },
    {
      "name": "Dart numerics",
      "scope": [
        "constant.numeric.dart",
      ],
      "settings": {
        "foreground": "#2EE2FA",
      }
    },
    {
      "name": "Scala variable params",
      "scope": [
        "variable.parameter.scala",
      ],
      "settings": {
        "foreground": "#2EE2FA",
      }
    },
    {
      "name": "Scala",
      "scope": [
        "meta.template.expression.scala",
      ],
      "settings": {
        "foreground": "#72f1b8",
      }
    },
  ],
  "colors": {
    "activityBar.background": "#282c34",
    "activityBar.foreground": "#d7dae0",
    "activityBarBadge.background": "#4d78cc",
    "activityBarBadge.foreground": "#f8fafd",
    "badge.background": "#282c34",
    "button.background": "#404754",
    "button.secondaryBackground": "#30333d",
    "button.secondaryForeground": "#c0bdbd",
    "checkbox.border": "#404754",
    "debugToolBar.background": "#21252b",
    "descriptionForeground": "#abb2bf",
    "diffEditor.insertedTextBackground": "#00809b33",
    "dropdown.background": "#21252b",
    "dropdown.border": "#21252b",
    "editor.background": "#282c34",
    "editor.findMatchBackground": "#d19a6644",
    "editor.findMatchBorder": "#ffffff5a",
    "editor.findMatchHighlightBackground": "#ffffff22",
    "editor.foreground": "#abb2bf",
    "editorBracketHighlight.foreground1": "#d19a66",
    "editorBracketHighlight.foreground2": "#c678dd",
    "editorBracketHighlight.foreground3": "#56b6c2",
    "editorHoverWidget.highlightForeground": "#61afef",
    "editorInlayHint.foreground": "#abb2bf",
    "editorInlayHint.background": "#2c313c",
    "editor.lineHighlightBackground": "#2c313c",
    "editorLineNumber.activeForeground": "#abb2bf",
    "editorGutter.addedBackground": "#109868",
    "editorGutter.deletedBackground": "#9A353D",
    "editorGutter.modifiedBackground": "#948B60",
    "editorOverviewRuler.addedBackground": "#109868",
    "editorOverviewRuler.deletedBackground": "#9A353D",
    "editorOverviewRuler.modifiedBackground": "#948B60",
    "editor.selectionBackground": "#67769660",
    "editor.selectionHighlightBackground": "#ffffff10",
    "editor.selectionHighlightBorder": "#dddddd",
    "editor.wordHighlightBackground": "#d2e0ff2f",
    "editor.wordHighlightBorder": "#7f848e",
    "editor.wordHighlightStrongBackground": "#abb2bf26",
    "editor.wordHighlightStrongBorder": "#7f848e",
    "editorBracketMatch.background": "#515a6b",
    "editorBracketMatch.border": "#515a6b",
    "editorCursor.background": "#ffffffc9",
    "editorCursor.foreground": "#528bff",
    "editorError.foreground": "#c24038",
    "editorGroup.background": "#181a1f",
    "editorGroup.border": "#181a1f",
    "editorGroupHeader.tabsBackground": "#21252b",
    "editorHoverWidget.background": "#21252b",
    "editorHoverWidget.border": "#181a1f",
    "editorIndentGuide.activeBackground": "#c8c8c859",
    "editorIndentGuide.background": "#3b4048",
    "editorLineNumber.foreground": "#495162",
    "editorMarkerNavigation.background": "#21252b",
    "editorRuler.foreground": "#abb2bf26",
    "editorSuggestWidget.background": "#21252b",
    "editorSuggestWidget.border": "#181a1f",
    "editorSuggestWidget.selectedBackground": "#2c313a",
    "editorWarning.foreground": "#d19a66",
    "editorWhitespace.foreground": "#ffffff1d",
    "editorWidget.background": "#21252b",
    "focusBorder": "#3e4452",
    "gitDecoration.ignoredResourceForeground": "#636b78",
    "input.background": "#1d1f23",
    "input.foreground": "#abb2bf",
    "list.activeSelectionBackground": "#2c313a",
    "list.activeSelectionForeground": "#d7dae0",
    "list.focusBackground": "#323842",
    "list.focusForeground": "#f0f0f0",
    "list.highlightForeground": "#ecebeb",
    "list.hoverBackground": "#2c313a",
    "list.hoverForeground": "#abb2bf",
    "list.inactiveSelectionBackground": "#323842",
    "list.inactiveSelectionForeground": "#d7dae0",
    "list.warningForeground": "#d19a66",
    "menu.foreground": "#abb2bf",
    "menu.separatorBackground": "#343a45",
    "minimapGutter.addedBackground": "#109868",
    "minimapGutter.deletedBackground": "#9A353D",
    "minimapGutter.modifiedBackground": "#948B60",
    "panel.border": "#3e4452",
    "panelSectionHeader.background": "#21252b",
    "peekViewEditor.background": "#1b1d23",
    "peekViewEditor.matchHighlightBackground": "#29244b",
    "peekViewResult.background": "#22262b",
    "scrollbar.shadow": "#23252c",
    "scrollbarSlider.activeBackground": "#747d9180",
    "scrollbarSlider.background": "#4e566660",
    "scrollbarSlider.hoverBackground": "#5a637580",
    "settings.focusedRowBackground": "#282c34",
    "settings.headerForeground": "#fff",
    "sideBar.background": "#21252b",
    "sideBar.foreground": "#abb2bf",
    "sideBarSectionHeader.background": "#282c34",
    "sideBarSectionHeader.foreground": "#abb2bf",
    "statusBar.background": "#21252b",
    "statusBar.debuggingBackground": "#cc6633",
    "statusBar.debuggingBorder": "#ff000000",
    "statusBar.debuggingForeground": "#ffffff",
    "statusBar.foreground": "#9da5b4",
    "statusBar.noFolderBackground": "#21252b",
    "statusBarItem.remoteBackground": "#4d78cc",
    "statusBarItem.remoteForeground": "#f8fafd",
    "tab.activeBackground": "#282c34",
    "tab.activeBorder": "#b4b4b4",
    "tab.activeForeground": "#dcdcdc",
    "tab.border": "#181a1f",
    "tab.hoverBackground": "#323842",
    "tab.inactiveBackground": "#21252b",
    "tab.unfocusedHoverBackground": "#323842",
    "terminal.ansiBlack": "#3f4451",
    "terminal.ansiBlue": "#4aa5f0",
    "terminal.ansiBrightBlack": "#4f5666",
    "terminal.ansiBrightBlue": "#4dc4ff",
    "terminal.ansiBrightCyan": "#4cd1e0",
    "terminal.ansiBrightGreen": "#a5e075",
    "terminal.ansiBrightMagenta": "#de73ff",
    "terminal.ansiBrightRed": "#ff616e",
    "terminal.ansiBrightWhite": "#e6e6e6",
    "terminal.ansiBrightYellow": "#f0a45d",
    "terminal.ansiCyan": "#42b3c2",
    "terminal.ansiGreen": "#8cc265",
    "terminal.ansiMagenta": "#c162de",
    "terminal.ansiRed": "#e05561",
    "terminal.ansiWhite": "#d7dae0",
    "terminal.ansiYellow": "#d18f52",
    "terminal.background": "#282c34",
    "terminal.border": "#3e4452",
    "terminal.foreground": "#abb2bf",
    "terminal.selectionBackground": "#abb2bf30",
    "textBlockQuote.background": "#2e3440",
    "textBlockQuote.border": "#4b5362",
    "textLink.foreground": "#61afef",
    "textPreformat.foreground": "#d19a66",
    "titleBar.activeBackground": "#282c34",
    "titleBar.activeForeground": "#9da5b4",
    "titleBar.inactiveBackground": "#282c34",
    "titleBar.inactiveForeground": "#6b717d",
    "tree.indentGuidesStroke": "#ffffff1d",
    "walkThrough.embeddedEditorBackground": "#2e3440",
    "welcomePage.buttonHoverBackground": "#404754"
  },
}
